{
  "forge_marker": 1,
  "defaults": {
    "model": "conquest:snowlayergravel_height2"
  },
  "variants": {
    "inventory": [
      {}
    ],
    "layers": {
      "1": {},
      "2": {
        "model": "conquest:snowlayergravel_height4"
      },
      "3": {
        "model": "conquest:snowlayergravel_height6"
      },
      "4": {
        "model": "conquest:snowlayergravel_height8"
      },
      "5": {
        "model": "conquest:snowlayergravel_height10"
      },
      "6": {
        "model": "conquest:snowlayergravel_height12"
      },
      "7": {
        "model": "conquest:snowlayergravel_height14"
      },
      "8": {
        "model": "conquest:snowlayergravel"
      }
    }
  }
}